kwork/__init__.py
kwork/api.py
kwork/bot.py
kwork/client.py
kwork/event_parser.py
kwork/exceptions.py
kwork/schema/__init__.py
kwork/schema/achievement.py
kwork/schema/actor.py
kwork/schema/category.py
kwork/schema/connects.py
kwork/schema/dialog.py
kwork/schema/event.py
kwork/schema/inbox.py
kwork/schema/kwork_object.py
kwork/schema/message.py
kwork/schema/portfolio.py
kwork/schema/project.py
kwork/schema/review.py
kwork/schema/user.py
kwork-0.1.1.dist-info/METADATA
kwork-0.1.1.dist-info/WHEEL
kwork-0.1.1.dist-info/top_level.txt
kwork-0.1.1.dist-info/RECORD
