Metadata-Version: 2.4
Name: kwork
Version: 0.1.1
Summary: Simple async wrapper for kwork.
Author: kesha1225
License-Expression: MIT
Project-URL: Homepage, https://github.com/kesha1225/pykwork
Project-URL: Repository, https://github.com/kesha1225/pykwork
Project-URL: Issues, https://github.com/kesha1225/pykwork/issues
Keywords: kwork,freelance,api,async,aiohttp,bot
Classifier: Development Status :: 4 - Beta
Classifier: Intended Audience :: Developers
Classifier: Operating System :: OS Independent
Classifier: Programming Language :: Python :: 3
Classifier: Programming Language :: Python :: 3.14
Classifier: Framework :: AsyncIO
Classifier: Typing :: Typed
Requires-Python: >=3.14
Requires-Dist: aiohttp>=3.13.2
Requires-Dist: pydantic>=2.12.5
Requires-Dist: websockets>=15.0.1
Provides-Extra: proxy
Requires-Dist: aiohttp-socks>=0.10.2; extra == "proxy"
